sslwatch/__init__.py
sslwatch/async_bulk.py
sslwatch/async_chain.py
sslwatch/async_watcher.py
sslwatch/bulk.py
sslwatch/certificate.py
sslwatch/chain.py
sslwatch/exceptions.py
sslwatch/hybrid_bulk.py
sslwatch/hybrid_watcher.py
sslwatch/logger.py
sslwatch/utils.py
sslwatch/watcher.py
sslwatch-0.0.1.dist-info/METADATA
sslwatch-0.0.1.dist-info/WHEEL
sslwatch-0.0.1.dist-info/top_level.txt
sslwatch-0.0.1.dist-info/RECORD
