Metadata-Version: 2.4
Name: sslwatch
Version: 0.0.1
Summary: Library Python untuk pemantauan sertifikat SSL/TLS
Home-page: https://github.com/yourname/sslwatch
Author: Your Name
Author-email: your.email@example.com
License: MIT
Project-URL: Documentation, https://github.com/yourname/sslwatch#readme
Project-URL: Source, https://github.com/yourname/sslwatch
Project-URL: Tracker, https://github.com/yourname/sslwatch/issues
Keywords: ssl tls certificate monitoring security
Classifier: Development Status :: 3 - Alpha
Classifier: Intended Audience :: Developers
Classifier: Topic :: Security :: Cryptography
Classifier: License :: OSI Approved :: MIT License
Classifier: Programming Language :: Python :: 3
Requires-Python: >=3.8
Provides-Extra: dev
Requires-Dist: pytest; extra == "dev"
Requires-Dist: black; extra == "dev"
Requires-Dist: flake8; extra == "dev"
Requires-Dist: mypy; extra == "dev"
Provides-Extra: docs
Requires-Dist: sphinx; extra == "docs"
Requires-Dist: sphinx-rtd-theme; extra == "docs"
Dynamic: author
Dynamic: author-email
Dynamic: classifier
Dynamic: description
Dynamic: description-content-type
Dynamic: home-page
Dynamic: keywords
Dynamic: license
Dynamic: project-url
Dynamic: provides-extra
Dynamic: requires-python
Dynamic: summary
